LICENSE
README.md
setup.cfg
setup.py
GroundingDinoCommit.egg-info/PKG-INFO
GroundingDinoCommit.egg-info/SOURCES.txt
GroundingDinoCommit.egg-info/dependency_links.txt
GroundingDinoCommit.egg-info/requires.txt
GroundingDinoCommit.egg-info/top_level.txt
groundingdino/__init__.py
groundingdino/version.py
groundingdino/datasets/__init__.py
groundingdino/datasets/transforms.py
groundingdino/models/__init__.py
groundingdino/models/registry.py
groundingdino/models/GroundingDINO/__init__.py
groundingdino/models/GroundingDINO/bertwarper.py
groundingdino/models/GroundingDINO/fuse_modules.py
groundingdino/models/GroundingDINO/groundingdino.py
groundingdino/models/GroundingDINO/ms_deform_attn.py
groundingdino/models/GroundingDINO/transformer.py
groundingdino/models/GroundingDINO/transformer_vanilla.py
groundingdino/models/GroundingDINO/utils.py
groundingdino/models/GroundingDINO/backbone/__init__.py
groundingdino/models/GroundingDINO/backbone/backbone.py
groundingdino/models/GroundingDINO/backbone/position_encoding.py
groundingdino/models/GroundingDINO/backbone/swin_transformer.py
groundingdino/util/__init__.py
groundingdino/util/box_ops.py
groundingdino/util/get_tokenlizer.py
groundingdino/util/inference.py
groundingdino/util/logger.py
groundingdino/util/misc.py
groundingdino/util/slconfig.py
groundingdino/util/slio.py
groundingdino/util/time_counter.py
groundingdino/util/utils.py
groundingdino/util/visualizer.py
groundingdino/util/vl_utils.py